justext/__init__.py
justext/__main__.py
justext/_compat.py
justext/core.py
justext/paragraph.py
justext/utils.py
justext/stoplists/Afrikaans.txt
justext/stoplists/Albanian.txt
justext/stoplists/Arabic.txt
justext/stoplists/Aragonese.txt
justext/stoplists/Armenian.txt
justext/stoplists/Aromanian.txt
justext/stoplists/Asturian.txt
justext/stoplists/Azerbaijani.txt
justext/stoplists/Basque.txt
justext/stoplists/Belarusian.txt
justext/stoplists/Belarusian_Taraskievica.txt
justext/stoplists/Bengali.txt
justext/stoplists/Bishnupriya_Manipuri.txt
justext/stoplists/Bosnian.txt
justext/stoplists/Breton.txt
justext/stoplists/Bulgarian.txt
justext/stoplists/Catalan.txt
justext/stoplists/Cebuano.txt
justext/stoplists/Chuvash.txt
justext/stoplists/Croatian.txt
justext/stoplists/Czech.txt
justext/stoplists/Danish.txt
justext/stoplists/Dutch.txt
justext/stoplists/English.txt
justext/stoplists/Esperanto.txt
justext/stoplists/Estonian.txt
justext/stoplists/Finnish.txt
justext/stoplists/French.txt
justext/stoplists/Galician.txt
justext/stoplists/Georgian.txt
justext/stoplists/German.txt
justext/stoplists/Greek.txt
justext/stoplists/Gujarati.txt
justext/stoplists/Haitian.txt
justext/stoplists/Hebrew.txt
justext/stoplists/Hindi.txt
justext/stoplists/Hungarian.txt
justext/stoplists/Icelandic.txt
justext/stoplists/Ido.txt
justext/stoplists/Igbo.txt
justext/stoplists/Indonesian.txt
justext/stoplists/Irish.txt
justext/stoplists/Italian.txt
justext/stoplists/Javanese.txt
justext/stoplists/Kannada.txt
justext/stoplists/Kazakh.txt
justext/stoplists/Korean.txt
justext/stoplists/Kurdish.txt
justext/stoplists/Kyrgyz.txt
justext/stoplists/Latin.txt
justext/stoplists/Latvian.txt
justext/stoplists/Lithuanian.txt
justext/stoplists/Lombard.txt
justext/stoplists/Low_Saxon.txt
justext/stoplists/Luxembourgish.txt
justext/stoplists/Macedonian.txt
justext/stoplists/Malay.txt
justext/stoplists/Malayalam.txt
justext/stoplists/Maltese.txt
justext/stoplists/Marathi.txt
justext/stoplists/Neapolitan.txt
jusText_lid-2.2.0.dist-info/LICENSE.rst
jusText_lid-2.2.0.dist-info/METADATA
jusText_lid-2.2.0.dist-info/WHEEL
jusText_lid-2.2.0.dist-info/top_level.txt
jusText_lid-2.2.0.dist-info/RECORD
