Metadata-Version: 2.1
Name: jusText-lid
Version: 2.2.0
Summary: jusText with language identification (fasttext) instead of stopwords
Home-page: https://github.com/miso-belica/jusText
Author: Jan Pomikálek
Author-email: jan.pomikalek@gmail.com
Maintainer: Jordi Armengol-Estapé
Maintainer-email: jordi.armengol.estape@gmail.com
License: The BSD 2-Clause License
Platform: UNKNOWN
Classifier: Development Status :: 5 - Production/Stable
Classifier: Intended Audience :: Developers
Classifier: Natural Language :: English
Classifier: License :: OSI Approved :: BSD License
Classifier: Operating System :: OS Independent
Classifier: Programming Language :: Python
Classifier: Programming Language :: Python :: 2
Classifier: Programming Language :: Python :: 2.7
Classifier: Programming Language :: Python :: 3
Classifier: Programming Language :: Python :: 3.4
Classifier: Programming Language :: Python :: 3.5
Classifier: Programming Language :: Python :: 3.6
Classifier: Programming Language :: Python :: 3.7
Classifier: Programming Language :: Python :: 3.8
Classifier: Programming Language :: Python :: Implementation :: CPython
Classifier: Topic :: Internet :: WWW/HTTP
Classifier: Topic :: Software Development :: Pre-processors
Classifier: Topic :: Text Processing :: Filters
Classifier: Topic :: Text Processing :: Markup :: HTML
License-File: LICENSE.rst
Requires-Dist: fasttext-langdetect-1.0.3
Requires-Dist: lxml (>=4.4.2) ; python_version == "2.7"
Requires-Dist: lxml (==4.3.5) ; python_version == "3.4"
Requires-Dist: lxml (>=4.4.2) ; python_version > "3.4"
